mfd_kvm/__init__.py
mfd_kvm/data_structures.py
mfd_kvm/exceptions.py
mfd_kvm/hypervisor.py
mfd_kvm/mdev_template.xml
mfd_kvm/pci_controller_template.xml
mfd_kvm/vf_template.xml
mfd_kvm/virsh.py
mfd_kvm-3.12.1.dist-info/licenses/AUTHORS.md
mfd_kvm-3.12.1.dist-info/licenses/LICENSE.md
mfd_kvm-3.12.1.dist-info/METADATA
mfd_kvm-3.12.1.dist-info/WHEEL
mfd_kvm-3.12.1.dist-info/top_level.txt
mfd_kvm-3.12.1.dist-info/RECORD
