Metadata-Version: 2.4
Name: mfd-kvm
Version: 3.12.1
Summary: Module for managing KVM hypervisors, enabling VM creation, control, and network device management.
Project-URL: Homepage, https://github.com/intel/mfd
Project-URL: Repository, https://github.com/intel/mfd-kvm
Project-URL: Issues, https://github.com/intel/mfd-kvm/issues
Project-URL: Changelog, https://github.com/intel/mfd-kvm/blob/main/CHANGELOG.md
Requires-Python: <3.14,>=3.10
License-File: LICENSE.md
License-File: AUTHORS.md
Requires-Dist: netaddr~=0.8.0
Requires-Dist: jinja2>=2.11
Requires-Dist: mfd_common_libs>=1.11.0
Requires-Dist: mfd-base-tool>=2.7.0
Requires-Dist: mfd_typing>=1.23.0
Dynamic: license-file
